wxpath/__init__.py
wxpath/cli.py
wxpath/patches.py
wxpath/settings.py
wxpath/tui.py
wxpath/tui_settings.py
wxpath/core/__init__.py
wxpath/core/dom.py
wxpath/core/models.py
wxpath/core/ops.py
wxpath/core/parser.py
wxpath/core/runtime/__init__.py
wxpath/core/runtime/engine.py
wxpath/core/runtime/helpers.py
wxpath/hooks/__init__.py
wxpath/hooks/builtin.py
wxpath/hooks/registry.py
wxpath/http/__init__.py
wxpath/http/stats.py
wxpath/http/client/__init__.py
wxpath/http/client/cache.py
wxpath/http/client/crawler.py
wxpath/http/client/request.py
wxpath/http/client/response.py
wxpath/http/policy/backoff.py
wxpath/http/policy/retry.py
wxpath/http/policy/robots.py
wxpath/http/policy/throttler.py
wxpath/integrations/__init__.py
wxpath/integrations/langchain/__init__.py
wxpath/integrations/langchain/loader.py
wxpath/integrations/langchain/examples/basic_rag.py
wxpath/integrations/langchain/examples/rolling_window_rag.py
wxpath/util/__init__.py
wxpath/util/cleaners.py
wxpath/util/common_paths.py
wxpath/util/logging.py
wxpath/util/serialize.py
wxpath-0.5.0.dist-info/licenses/LICENSE
wxpath-0.5.0.dist-info/METADATA
wxpath-0.5.0.dist-info/WHEEL
wxpath-0.5.0.dist-info/entry_points.txt
wxpath-0.5.0.dist-info/top_level.txt
wxpath-0.5.0.dist-info/RECORD
