Metadata-Version: 2.4
Name: wxpath
Version: 0.5.0
Summary: wxpath - a declarative web crawler and data extractor
Author-email: Rodrigo Palacios <rodrigopala91@gmail.com>
License-Expression: MIT
Project-URL: Homepage, https://rodricios.github.io/wxpath
Project-URL: Documentation, https://rodricios.github.io/wxpath
Project-URL: Repository, https://github.com/rodricios/wxpath
Project-URL: Issues, https://github.com/rodricios/wxpath/issues
Project-URL: Changelog, https://github.com/rodricios/wxpath/blob/main/CHANGELOG.md
Requires-Python: >=3.10
License-File: LICENSE
Requires-Dist: lxml>=4.0
Requires-Dist: elementpath<=5.0.3,>=5.0.0
Requires-Dist: aiohttp<=3.12.15,>=3.8.0
Requires-Dist: tqdm>=4.0.0
Provides-Extra: cache
Requires-Dist: aiohttp-client-cache>=0.14.0; extra == "cache"
Provides-Extra: cache-sqlite
Requires-Dist: aiohttp-client-cache[sqlite]; extra == "cache-sqlite"
Provides-Extra: cache-redis
Requires-Dist: aiohttp-client-cache[redis]; extra == "cache-redis"
Provides-Extra: llm
Requires-Dist: langchain>=1.0.0; extra == "llm"
Requires-Dist: langchain-core>=1.0.0; extra == "llm"
Requires-Dist: langchain-ollama>=1.0.0; extra == "llm"
Requires-Dist: langchain-community>=0.4.0; extra == "llm"
Requires-Dist: langchain-chroma>=1.0.0; extra == "llm"
Requires-Dist: chromadb>=1.0.0; extra == "llm"
Requires-Dist: langchain-text-splitters>=1.1.0; extra == "llm"
Provides-Extra: test
Requires-Dist: pytest>=7.0; extra == "test"
Requires-Dist: pytest-asyncio>=0.23; extra == "test"
Provides-Extra: dev
Requires-Dist: ruff; extra == "dev"
Provides-Extra: docs
Requires-Dist: mkdocs>=1.5; extra == "docs"
Requires-Dist: mkdocs-material>=9.0; extra == "docs"
Requires-Dist: mkdocstrings[python]>=0.24; extra == "docs"
Requires-Dist: mkdocs-macros-plugin>=1.0; extra == "docs"
Requires-Dist: mkdocs-resize-images>=1.0; extra == "docs"
Requires-Dist: mkdocs-glightbox; extra == "docs"
Requires-Dist: pyyaml>=6.0; extra == "docs"
Provides-Extra: tui
Requires-Dist: textual>=1.0.0; extra == "tui"
Requires-Dist: aiohttp-client-cache>=0.14.0; extra == "tui"
Requires-Dist: aiohttp-client-cache[sqlite]; extra == "tui"
Dynamic: license-file
